shiertier_image/__init__.py
shiertier_image/image.py
shiertier_image/image2.py
shiertier_image-0.1.3.dist-info/LICENSE
shiertier_image-0.1.3.dist-info/METADATA
shiertier_image-0.1.3.dist-info/WHEEL
shiertier_image-0.1.3.dist-info/top_level.txt
shiertier_image-0.1.3.dist-info/RECORD
