Metadata-Version: 2.1
Name: shiertier_image
Version: 0.1.3
Summary: A simple image processing library for Python.
Author-email: shiertier <junjie.text@gmail.com>
License: MIT License
Classifier: Development Status :: 3 - Alpha
Classifier: Intended Audience :: Developers
Classifier: License :: OSI Approved :: MIT License
Classifier: Programming Language :: Python :: 3
Classifier: Programming Language :: Python :: 3.7
Classifier: Programming Language :: Python :: 3.8
Classifier: Programming Language :: Python :: 3.9
Classifier: Programming Language :: Python :: 3.10
Classifier: Programming Language :: Python :: 3.11
Classifier: Programming Language :: Python :: 3.12
Requires-Python: >=3.7
License-File: LICENSE
Requires-Dist: Pillow
Requires-Dist: shiertier-logger
Requires-Dist: numpy
Requires-Dist: opencv-python
